markdown_changelog/__init__.py
markdown_changelog/changelog.py
tests/__init__.py
tests/test_changelog.py
markdown_changelog-0.0.4.dist-info/LICENSE
markdown_changelog-0.0.4.dist-info/METADATA
markdown_changelog-0.0.4.dist-info/WHEEL
markdown_changelog-0.0.4.dist-info/entry_points.txt
markdown_changelog-0.0.4.dist-info/top_level.txt
markdown_changelog-0.0.4.dist-info/RECORD
